tgfilestream/__init__.py
tgfilestream/__main__.py
tgfilestream/cache_util.py
tgfilestream/config.py
tgfilestream/log.py
tgfilestream/paralleltransfer.py
tgfilestream/start.py
tgfilestream/telegram.py
tgfilestream/util.py
tgfilestream/web_routes.py
tgfilestream-0.1.4.dist-info/licenses/LICENSE
tgfilestream-0.1.4.dist-info/METADATA
tgfilestream-0.1.4.dist-info/WHEEL
tgfilestream-0.1.4.dist-info/entry_points.txt
tgfilestream-0.1.4.dist-info/top_level.txt
tgfilestream-0.1.4.dist-info/RECORD
