Metadata-Version: 2.4
Name: tgfilestream
Version: 0.1.4
Summary: A Telegram bot that can stream Telegram files to users over HTTP.
Home-page: https://mau.dev/tulir/TGFileStream
Author: Tulir Asokan
Author-email: tulir@maunium.net
License: AGPL-3.0-or-later
Classifier: Development Status :: 4 - Beta
Classifier: License :: OSI Approved :: GNU Affero General Public License v3 or later (AGPLv3+)
Classifier: Framework :: AsyncIO
Classifier: Programming Language :: Python
Classifier: Programming Language :: Python :: 3
Classifier: Programming Language :: Python :: 3.7
Classifier: Programming Language :: Python :: 3.8
Requires-Python: ~=3.7
License-File: LICENSE
Requires-Dist: aiohttp>=3
Requires-Dist: telethon>=1.10
Requires-Dist: yarl>=1
Provides-Extra: env
Requires-Dist: python-dotenv>=0.20; extra == "env"
Provides-Extra: fast
Requires-Dist: cryptg>=0.2; extra == "fast"
Provides-Extra: all
Requires-Dist: cryptg>=0.2; extra == "all"
Requires-Dist: python-dotenv>=0.20; extra == "all"
Dynamic: author
Dynamic: author-email
Dynamic: classifier
Dynamic: description
Dynamic: description-content-type
Dynamic: home-page
Dynamic: license
Dynamic: license-file
Dynamic: provides-extra
Dynamic: requires-dist
Dynamic: requires-python
Dynamic: summary
